ssh_websocket/__init__.py
ssh_websocket/dns_server.py
ssh_websocket/ssh_client.py
ssh_websocket/ssh_server.py
ssh_websocket-0.0.8.dist-info/METADATA
ssh_websocket-0.0.8.dist-info/RECORD
ssh_websocket-0.0.8.dist-info/WHEEL
ssh_websocket-0.0.8.dist-info/entry_points.txt
ssh_websocket-0.0.8.dist-info/top_level.txt
