Metadata-Version: 2.1
Name: ssh-websocket
Version: 0.0.8
Summary: A Stable implementation of a SSH server over websocket
Home-page: https://github.com/nwmqpa/SSHWebSocket
Author: Thomas Nicollet
Author-email: thomas.nicollet@epitech.eu
License: UNKNOWN
Platform: UNKNOWN
Classifier: Programming Language :: Python :: 3
Classifier: License :: OSI Approved :: GNU General Public License v3 (GPLv3)
Classifier: Operating System :: OS Independent
Requires-Dist: twisted
Requires-Dist: autobahn
Requires-Dist: websocket-client
Requires-Dist: websockets
